supereasypypi/__init__.py
supereasypypi/__main__.py
supereasypypi/cli.py
supereasypypi/template.py
super_easypypi-0.0.10.dist-info/LICENSE
super_easypypi-0.0.10.dist-info/METADATA
super_easypypi-0.0.10.dist-info/WHEEL
super_easypypi-0.0.10.dist-info/entry_points.txt
super_easypypi-0.0.10.dist-info/top_level.txt
super_easypypi-0.0.10.dist-info/RECORD
